vultrexbots/__init__.py
vultrexbots/client.py
vultrexbots/lib/__init__.py
vultrexbots/lib/util/__init__.py
vultrexbots/lib/util/exceptions.py
vultrexbots/lib/util/objects.py
vultrexbots.py-0.0.6.dist-info/LICENSE
vultrexbots.py-0.0.6.dist-info/METADATA
vultrexbots.py-0.0.6.dist-info/WHEEL
vultrexbots.py-0.0.6.dist-info/top_level.txt
vultrexbots.py-0.0.6.dist-info/RECORD
