Metadata-Version: 2.1
Name: vultrexbots.py
Version: 0.0.6
Summary: API wrapper for vultrexbots
Home-page: https://github.com/wezacon/vultrexbots.py
Author: Team Wezacon
Author-email: wezacon.com@gmail.com
License: AGPL
Download-URL: https://github.com/wezacon/vultrexbots.py/tarball/master
Keywords: vultrex,bots-py,wezacon
Platform: UNKNOWN
Requires-Dist: setuptools
Requires-Dist: requests
Requires-Dist: six
Requires-Dist: ujson
